DnD4py/__init__.py
DnD4py/lookup_5e.py
DnD4py/roll4me.py
DnD4py-1.0.5.dist-info/LICENSE
DnD4py-1.0.5.dist-info/METADATA
DnD4py-1.0.5.dist-info/WHEEL
DnD4py-1.0.5.dist-info/entry_points.txt
DnD4py-1.0.5.dist-info/top_level.txt
DnD4py-1.0.5.dist-info/RECORD
