Metadata-Version: 2.1
Name: DnD4py
Version: 1.0.5
Summary: Python Codes for DnD 5e
Home-page: https://github.com/bacook17/DnD4py/
Author: Ben Cook
Author-email: bacook17@gmail.com
License: LICENSE
Keywords: games,Dungeons and Dragons
Platform: UNKNOWN
Classifier: Topic :: Games/Entertainment :: Role-Playing
Classifier: Programming Language :: Python
Requires-Dist: numpy
Requires-Dist: bs4
Requires-Dist: requests
Requires-Dist: pypandoc
